chromalog/colorizer.py
chromalog/log.py
chromalog/stream.py
chromalog/__init__.py
chromalog/mark/helpers.py
chromalog/mark/objects.py
chromalog/mark/__init__.py
chromalog-1.0.5.dist-info/DESCRIPTION.rst
chromalog-1.0.5.dist-info/METADATA
chromalog-1.0.5.dist-info/metadata.json
chromalog-1.0.5.dist-info/RECORD
chromalog-1.0.5.dist-info/top_level.txt
chromalog-1.0.5.dist-info/WHEEL
