Metadata-Version: 2.0
Name: chromalog
Version: 1.0.5
Summary: A non-intrusive way to use colors in your logs and generic output.
Home-page: http://chromalog.readthedocs.org/en/latest/index.html
Author: Julien Kauffmann
Author-email: julien.kauffmann@freelan.org
License: MIT
Platform: UNKNOWN
Classifier: Intended Audience :: Developers
Classifier: Operating System :: OS Independent
Classifier: Programming Language :: Python :: 2
Classifier: Programming Language :: Python :: 2.6
Classifier: Programming Language :: Python :: 2.7
Classifier: Programming Language :: Python :: 3
Classifier: Programming Language :: Python :: 3.3
Classifier: Programming Language :: Python :: 3.4
Classifier: Programming Language :: Python :: 3.5
Classifier: Topic :: Software Development
Classifier: Topic :: Software Development :: Libraries :: Python Modules
Classifier: License :: OSI Approved :: MIT License
Classifier: Development Status :: 5 - Production/Stable
Requires-Dist: colorama (>=0.3.7)
Requires-Dist: future (>=0.14.3)
Requires-Dist: six (>=1.9.0,<2)
